Dellingr/AdapterPredict.py
Dellingr/Call.py
Dellingr/ClipOverlap.py
Dellingr/Collapse.py
Dellingr/DellingrExceptions.py
Dellingr/DellingrPipeline.py
Dellingr/ResumePipeline.py
Dellingr/SplitMerge.py
Dellingr/Train.py
Dellingr/Trim.py
Dellingr/UpdateConfig.py
Dellingr/__init__.py
Dellingr/__version.py
Dellingr/default_filter.pkl
Dellingr-0.9.5.data/scripts/dellingr
Dellingr-0.9.5.dist-info/LICENSE.txt
Dellingr-0.9.5.dist-info/METADATA
Dellingr-0.9.5.dist-info/WHEEL
Dellingr-0.9.5.dist-info/top_level.txt
Dellingr-0.9.5.dist-info/RECORD
