Metadata-Version: 2.1
Name: Dellingr
Version: 0.9.5
Summary: Error supression and variant calling pipeline for Illumina sequencing data
Home-page: https://github.com/morinlab/Dellingr
Author: Christopher Rushton
Author-email: ckrushto@sfu.ca
License: UNKNOWN
Download-URL: https://github.com/morinlab/Dellingr/dist/Dellingr-0.9.5.tar.gz
Project-URL: Source, https://github.com/morinlab/Dellingr
Project-URL: Documentation, https://dellingr.readthedocs.io/en/latest/
Platform: UNKNOWN
Classifier: Programming Language :: Python :: 3
Classifier: Operating System :: Unix
Classifier: Topic :: Scientific/Engineering :: Bio-Informatics
Classifier: License :: OSI Approved :: GNU Affero General Public License v3
Requires-Python: >=3.5
Requires-Dist: cython
Requires-Dist: seaborn
Requires-Dist: scipy
Requires-Dist: fisher
Requires-Dist: sortedcontainers
Requires-Dist: configobj
Requires-Dist: packaging
Requires-Dist: pyfaidx
Requires-Dist: pysam (!=0.15.3)
Requires-Dist: scikit-learn (==0.22.1)
Requires-Dist: scikit-bio
Requires-Dist: numpy
